{
  "honmei":1,
  "label": "一白水星",
  "yuki": [

     { "date":"2026-04-13", "times":["15:00-17:00"], "dirs":["南西"] },

 { "date":"2026-05-09", "times":["01:00-03:00","19:00-21:00"], "dirs":["西"] },
 { "date":"2026-05-18", "times":["01:00-03:00","19:00-21:00"], "dirs":["西"] },
 { "date":"2026-05-27", "times":["01:00-03:00","19:00-21:00"], "dirs":["西"] },
 { "date":"2026-06-05", "times":["01:00-03:00","19:00-21:00"], "dirs":["西"] },

{ "date":"2026-06-13", "times":["05:00-07:00"], "dirs":["西"] },
{ "date":"2026-06-24", "times":["05:00-07:00"], "dirs":["西"] },
{ "date":"2026-07-03", "times":["05:00-07:00"], "dirs":["西"] },

   { "date":"2026-07-13", "times":["11:00-13:00"], "dirs":["東北東"] },

 { "date":"2026-08-10", "times":["07:00-09:00"], "dirs":["西"] },
 { "date":"2026-08-19", "times":["07:00-09:00"], "dirs":["西"] },
 { "date":"2026-08-28", "times":["07:00-09:00"], "dirs":["西"] },
 { "date":"2026-09-06", "times":["07:00-09:00"], "dirs":["西"] },

       { "date":"2026-09-07", "times":["03:00-05:00","21:00-23:00"], "dirs":["東北","南西","西"] },
      { "date":"2026-09-16", "times":["03:00-05:00","21:00-23:00"], "dirs":["東北","南西","西"] },
      { "date":"2026-09-25", "times":["03:00-05:00","21:00-23:00"], "dirs":["東北","南西","西"] },
      { "date":"2026-10-04", "times":["03:00-05:00","21:00-23:00"], "dirs":["東北","南西","西"] },

{ "date":"2026-10-14", "times":["23:00-01:00","17:00-19:00"], "dirs":["東北","南西"] }

     ]
  }
